exttr/__init__.py
exttr/_utility.py
exttr/_version.py
exttr/core.py
exttr/tests/__init__.py
exttr/tests/test_.py
exttr-2019.2.2.dist-info/LICENSE
exttr-2019.2.2.dist-info/METADATA
exttr-2019.2.2.dist-info/WHEEL
exttr-2019.2.2.dist-info/top_level.txt
exttr-2019.2.2.dist-info/RECORD
